multikiwilogger/__init__.py
multikiwilogger/multikiwilogger.py
multikiwilogger-1.1.0.dist-info/LICENSE
multikiwilogger-1.1.0.dist-info/METADATA
multikiwilogger-1.1.0.dist-info/WHEEL
multikiwilogger-1.1.0.dist-info/top_level.txt
multikiwilogger-1.1.0.dist-info/RECORD
